ideuy/__init__.py
ideuy/download.py
ideuy/query.py
ideuy/vector.py
ideuy/console/download.py
ideuy/console/filter.py
ideuy/data/national_grid.geojson
ideuy/data/urban_grid.geojson
ideuy-0.1.0.dist-info/AUTHORS.rst
ideuy-0.1.0.dist-info/LICENSE.txt
ideuy-0.1.0.dist-info/METADATA
ideuy-0.1.0.dist-info/WHEEL
ideuy-0.1.0.dist-info/entry_points.txt
ideuy-0.1.0.dist-info/top_level.txt
ideuy-0.1.0.dist-info/RECORD
