Metadata-Version: 2.1
Name: ideuy
Version: 0.1.0
Summary: Add a short description here!
Home-page: https://github.com/pyscaffold/pyscaffold/
Author: Damián Silvani
Author-email: munshkr@gmail.com
License: mit
Project-URL: Documentation, https://pyscaffold.org/
Platform: any
Classifier: Development Status :: 4 - Beta
Classifier: Programming Language :: Python
Requires-Dist: requests
Requires-Dist: tqdm
Requires-Dist: fiona
Requires-Dist: shapely
Requires-Dist: pyproj
Provides-Extra: testing
Requires-Dist: pytest ; extra == 'testing'
Requires-Dist: pytest-cov ; extra == 'testing'
